LICENSE
MANIFEST.in
README.md
pyproject.toml
setup.py
src/__init__.py
src/ansidocs/__init__.py
src/ansidocs/command_line.py
src/ansidocs/main.py
src/ansidocs.egg-info/PKG-INFO
src/ansidocs.egg-info/SOURCES.txt
src/ansidocs.egg-info/dependency_links.txt
src/ansidocs.egg-info/entry_points.txt
src/ansidocs.egg-info/requires.txt
src/ansidocs.egg-info/top_level.txt
src/ansidocs/classes/__init__.py
src/ansidocs/classes/abstract_project_part.py
src/ansidocs/classes/exceptions.py
src/ansidocs/classes/layout.py
src/ansidocs/classes/project.py
src/ansidocs/classes/project_parts/__init__.py
src/ansidocs/classes/project_parts/defaults.py
src/ansidocs/classes/project_parts/meta.py
src/ansidocs/classes/project_parts/playbooks.py
src/ansidocs/classes/project_parts/plugins.py
src/ansidocs/classes/project_parts/roles.py
src/ansidocs/classes/static/config.py
src/ansidocs/classes/static/readme_writer.py
src/ansidocs/config/ansidocs.yml
src/ansidocs/config/templates/collection/usage.md.j2
src/ansidocs/config/templates/defaults/README.md.j2
src/ansidocs/config/templates/defaults/description.md.j2
src/ansidocs/config/templates/defaults/footer.md.j2
src/ansidocs/config/templates/defaults/usage.md.j2
src/ansidocs/config/templates/role/usage.md.j2