Metadata-Version: 2.1
Name: ansidocs
Version: 1.0.6
Summary: Generate and collate documentation for Ansible projects
Author-email: Mike Morency <mikemorency93@gmail.com>
License: Copyright (c) 2018 The Python Packaging Authority
Project-URL: homepage, https://github.com/mikemorency/ansidocs
Project-URL: repository, https://github.com/mikemorency/ansidocs
Project-URL: documentation, https://github.com/mikemorency/ansidocs
Keywords: ansible,documentation,generator,generate
Classifier: Programming Language :: Python :: 3
Classifier: License :: OSI Approved :: MIT License
Classifier: Operating System :: OS Independent
Requires-Python: >=3.8
Provides-Extra: dev
License-File: LICENSE
